k3testdocumentation_generator/__init__.py
k3testdocumentation_generator/_version.py
k3testdocumentation_generator/api_impl.py
k3testdocumentation_generator/main/__init__.py
k3testdocumentation_generator/main/cli.py
k3testdocumentation_generator/main/gen_coverage_cli.py
k3testdocumentation_generator/resources/__init__.py
k3testdocumentation_generator/resources/testdocumentation_coverage.html
k3testdocumentation_generator/resources/testdocumentation_template.html
k3testdocumentation_generator-0.3.0.dist-info/LICENSE
k3testdocumentation_generator-0.3.0.dist-info/METADATA
k3testdocumentation_generator-0.3.0.dist-info/WHEEL
k3testdocumentation_generator-0.3.0.dist-info/entry_points.txt
k3testdocumentation_generator-0.3.0.dist-info/top_level.txt
k3testdocumentation_generator-0.3.0.dist-info/RECORD
