Metadata-Version: 2.1
Name: k3testdocumentation-generator
Version: 0.3.0
Summary: Tool for generating test documentation
Home-page: UNKNOWN
Author: Joachim Kestner
Author-email: joachim.kester@khoch3.de
License: UNKNOWN
Platform: UNKNOWN
Classifier: Programming Language :: Python :: 3
Classifier: License :: OSI Approved :: MIT License
Classifier: Operating System :: POSIX :: Linux
Requires-Python: ~=3.6
Requires-Dist: k3logging (==0.1)
Requires-Dist: Jinja2
Requires-Dist: pdfkit
Requires-Dist: markdown
Requires-Dist: pypandoc
